maxpanda_python_sdk/__init__.py
maxpanda_python_sdk/api_client.py
maxpanda_python_sdk/configuration.py
maxpanda_python_sdk/rest.py
maxpanda_python_sdk/api/__init__.py
maxpanda_python_sdk/api/asset_status_api.py
maxpanda_python_sdk/api/asset_type_api.py
maxpanda_python_sdk/api/assets_api.py
maxpanda_python_sdk/api/bins_api.py
maxpanda_python_sdk/api/buildings_api.py
maxpanda_python_sdk/api/customer_api.py
maxpanda_python_sdk/api/customer_invoices_api.py
maxpanda_python_sdk/api/department_api.py
maxpanda_python_sdk/api/invoice_item_tax_api.py
maxpanda_python_sdk/api/invoice_item_type_api.py
maxpanda_python_sdk/api/location_api.py
maxpanda_python_sdk/api/location_type_api.py
maxpanda_python_sdk/api/metering_type_api.py
maxpanda_python_sdk/api/part_category_api.py
maxpanda_python_sdk/api/part_status_api.py
maxpanda_python_sdk/api/parts_api.py
maxpanda_python_sdk/api/po_address_api.py
maxpanda_python_sdk/api/po_templates_api.py
maxpanda_python_sdk/api/purchase_orders_api.py
maxpanda_python_sdk/api/service_types_api.py
maxpanda_python_sdk/api/sites_api.py
maxpanda_python_sdk/api/task_fields_api.py
maxpanda_python_sdk/api/task_priority_api.py
maxpanda_python_sdk/api/task_status_api.py
maxpanda_python_sdk/api/tasks_api.py
maxpanda_python_sdk/api/users_api.py
maxpanda_python_sdk/api/vendor_api.py
maxpanda_python_sdk/api/vendor_invoices_api.py
maxpanda_python_sdk/api/work_order_category_api.py
maxpanda_python_sdk/api/work_order_priority_api.py
maxpanda_python_sdk/api/work_orders_api.py
maxpanda_python_sdk/models/__init__.py
maxpanda_python_sdk/models/address.py
maxpanda_python_sdk/models/address_api_model.py
maxpanda_python_sdk/models/api_address_model.py
maxpanda_python_sdk/models/asset.py
maxpanda_python_sdk/models/asset_audit_model.py
maxpanda_python_sdk/models/asset_create_update_response_model.py
maxpanda_python_sdk/models/asset_list.py
maxpanda_python_sdk/models/asset_ref.py
maxpanda_python_sdk/models/asset_response_model.py
maxpanda_python_sdk-0.0.4.dist-info/LICENSE
maxpanda_python_sdk-0.0.4.dist-info/METADATA
maxpanda_python_sdk-0.0.4.dist-info/WHEEL
maxpanda_python_sdk-0.0.4.dist-info/top_level.txt
maxpanda_python_sdk-0.0.4.dist-info/RECORD
